pyamldantic/__init__.py
pyamldantic/config.py
pyamldantic/exceptions.py
pyamldantic-1.3.0.dist-info/METADATA
pyamldantic-1.3.0.dist-info/WHEEL
pyamldantic-1.3.0.dist-info/licenses/LICENSE
pyamldantic-1.3.0.dist-info/RECORD
