Metadata-Version: 2.4
Name: pyamldantic
Version: 1.3.0
Summary: Validate and serialize YAML config files with Pydantic, with support for environment variables.
Project-URL: Homepage, https://github.com/stefanofusai/pyamldantic
Project-URL: Repository, https://github.com/stefanofusai/pyamldantic
Author-email: Stefano Fusai <stefanofusai@gmail.com>
Maintainer-email: Stefano Fusai <stefanofusai@gmail.com>
License-File: LICENSE
Requires-Python: >=3.12
Requires-Dist: pydantic<3.0.0,>=2.8.0
Requires-Dist: pyyaml<7.0.0,>=6.0.1
